va/__init__.py
va/mainva.py
va/preparation.py
va/qscores.csv
va/validationanalysis.py
va/version.py
va/metrics/__init__.py
va/metrics/bars.py
va/metrics/emda_mmcc.py
va/metrics/emringer.py
va/metrics/phenix_cc.py
va/metrics/phenix_mm.py
va/metrics/qscore.py
va/metrics/strudel.py
va/metrics/threedfsc.py
va/utils/Checker.py
va/utils/__init__.py
va/utils/misc.py
va/utils/rescolor.py
va-0.0.1.dev132.dist-info/METADATA
va-0.0.1.dev132.dist-info/WHEEL
va-0.0.1.dev132.dist-info/entry_points.txt
va-0.0.1.dev132.dist-info/top_level.txt
va-0.0.1.dev132.dist-info/RECORD
